<?xml version="1.0" encoding="UTF-8"?>
<MF0 version="1.1">
    <ModelRefInfoRepo.ModelRefInfoRoot type="ModelRefInfoRepo.ModelRefInfoRoot" uuid="2bf44137-3068-4466-b142-a091a788552a">
        <dataDictionary/>
        <dataTransferInfos>AAFJTQAAAAAOAAAAOAAAAAYAAAAIAAAAAgAAAAAAAAAFAAAACAAAAAAAAAABAAAAAQAAAAAAAAAFAAQAAQAAAAEAAAAAAAAA</dataTransferInfos>
        <hasInlineVariantBlock>false</hasInlineVariantBlock>
        <hasMachineDataAccess>false</hasMachineDataAccess>
        <hasSigObjWithICDrivingRootOutport>false</hasSigObjWithICDrivingRootOutport>
        <inports type="ModelRefInfoRepo.InportInformation" uuid="5b5e9cfd-62ad-4c27-aba2-084c1549a294">
            <EMVCE/>
            <originalPortNumber>0</originalPortNumber>
        </inports>
        <inports type="ModelRefInfoRepo.InportInformation" uuid="e35a9834-a7ab-4c12-869b-b24ca21220ea">
            <EMVCE/>
            <originalPortNumber>1</originalPortNumber>
        </inports>
        <inports type="ModelRefInfoRepo.InportInformation" uuid="7bb429c8-cfc4-4be9-bd70-bfde12f13016">
            <EMVCE/>
            <originalPortNumber>2</originalPortNumber>
        </inports>
        <inports type="ModelRefInfoRepo.InportInformation" uuid="60a45b2d-bdf0-4aed-972b-d1460805cea5">
            <EMVCE/>
            <originalPortNumber>3</originalPortNumber>
        </inports>
        <inports type="ModelRefInfoRepo.InportInformation" uuid="c24ad293-4625-4a2c-8728-8e43bea3fd42">
            <EMVCE/>
            <originalPortNumber>4</originalPortNumber>
        </inports>
        <inports type="ModelRefInfoRepo.InportInformation" uuid="9577a067-037d-4fca-b86c-cdb8d9be3239">
            <EMVCE/>
            <originalPortNumber>5</originalPortNumber>
        </inports>
        <inports type="ModelRefInfoRepo.InportInformation" uuid="b3884bed-5153-43c9-be2b-769e17bb5674">
            <EMVCE/>
            <originalPortNumber>6</originalPortNumber>
        </inports>
        <isOrigInportVirtualBus>false</isOrigInportVirtualBus>
        <isOrigInportVirtualBus>false</isOrigInportVirtualBus>
        <isOrigInportVirtualBus>false</isOrigInportVirtualBus>
        <isOrigInportVirtualBus>false</isOrigInportVirtualBus>
        <isOrigInportVirtualBus>false</isOrigInportVirtualBus>
        <isOrigInportVirtualBus>false</isOrigInportVirtualBus>
        <isOrigInportVirtualBus>false</isOrigInportVirtualBus>
        <isOrigOutportVirtualBus>false</isOrigOutportVirtualBus>
        <isOrigOutportVirtualBus>false</isOrigOutportVirtualBus>
        <isOrigOutportVirtualBus>false</isOrigOutportVirtualBus>
        <isOrigOutportVirtualBus>false</isOrigOutportVirtualBus>
        <isOrigOutportVirtualBus>false</isOrigOutportVirtualBus>
        <isOrigOutportVirtualBus>false</isOrigOutportVirtualBus>
        <needElapsedTime>false</needElapsedTime>
        <outports type="ModelRefInfoRepo.OutportInformation" uuid="9a664f63-57ab-4482-8ddf-4b489178e2a4">
            <EMVCE/>
            <originalPortNumber>0</originalPortNumber>
        </outports>
        <outports type="ModelRefInfoRepo.OutportInformation" uuid="520ac06a-1cd6-4fbc-a5f2-e0139a732c39">
            <EMVCE/>
            <originalPortNumber>1</originalPortNumber>
        </outports>
        <outports type="ModelRefInfoRepo.OutportInformation" uuid="44d86c08-76ff-4db0-b1a5-43e85d5dc75a">
            <EMVCE/>
            <originalPortNumber>2</originalPortNumber>
        </outports>
        <outports type="ModelRefInfoRepo.OutportInformation" uuid="ada9c446-6a86-4659-bfa5-462f00398c4a">
            <EMVCE/>
            <originalPortNumber>3</originalPortNumber>
        </outports>
        <outports type="ModelRefInfoRepo.OutportInformation" uuid="b70c50d7-33f9-49aa-bacf-0e075bcefdfb">
            <EMVCE/>
            <originalPortNumber>4</originalPortNumber>
        </outports>
        <outports type="ModelRefInfoRepo.OutportInformation" uuid="f4dffdb9-175b-4281-a85c-5726c8b87175">
            <EMVCE/>
            <originalPortNumber>5</originalPortNumber>
        </outports>
        <userSpecifiedFixedStepSize>0</userSpecifiedFixedStepSize>
        <zeroInternalMemoryAtStartupUnchecked>false</zeroInternalMemoryAtStartupUnchecked>
        <FMUBlockMap type="ModelRefInfoRepo.FMUBlockInfo" uuid="abe28c5a-b8bc-481f-9ae9-d47494266eb1"/>
        <periodicEventPortUnsupportedBlockInfo type="ModelRefInfoRepo.PeriodicEventPortUnsupportedBlockInfo" uuid="3276aa7c-fb66-433c-9305-cad0918563db">
            <hasHiddenDeterministicRTB>false</hasHiddenDeterministicRTB>
        </periodicEventPortUnsupportedBlockInfo>
        <simulinkFunctions type="ModelRefInfoRepo.SimulinkFunctions" uuid="65ef85d5-8d5f-41b4-87e9-154a1968b270">
            <compSimulinkFunctionCatalog>AAFJTQAAAAAOAAAAgAAAAAYAAAAIAAAAAgAAAAAAAAAFAAAACAAAAAEAAAABAAAAAQAAAAAAAAAFAAQADgAAAAEAAAAOAAAAQ29tcEZ1bmN0aW9ucwAAAA4AAAAwAAAABgAAAAgAAAAGAAAAAAAAAAUAAAAIAAAAAAAAAAAAAAABAAAAAAAAAAkAAAAAAAAA</compSimulinkFunctionCatalog>
            <postPropHasAnyExportedFunction>false</postPropHasAnyExportedFunction>
            <postPropHasAnyVariantExportedFunction>false</postPropHasAnyVariantExportedFunction>
        </simulinkFunctions>
    </ModelRefInfoRepo.ModelRefInfoRoot>
</MF0>
